maryChain/__init__.py
maryChain/maryChain.py
maryChain/maryChainAST.py
maryChain/parsetab.py
maryChain-0.0.3.dist-info/LICENSE
maryChain-0.0.3.dist-info/METADATA
maryChain-0.0.3.dist-info/WHEEL
maryChain-0.0.3.dist-info/top_level.txt
maryChain-0.0.3.dist-info/RECORD
