Metadata-Version: 2.1
Name: maryChain
Version: 0.0.3
Summary: maryChain - lightweight programming functional language for LLM
Home-page: https://github.com/alessioricco/maryChain
Download-URL: https://github.com/alessioricco/maryChain/releases/tag/v0.0.3
Author: Alessio Ricco
Author-email: alessio.ricco@gmail.com
License: MIT
Project-URL: Bug Tracker, https://github.com/alessioricco/maryChain/issues
Keywords: pypi,maryChain,programming language,functional,ai,llm
Classifier: Development Status :: 2 - Pre-Alpha
Classifier: Intended Audience :: Developers
Classifier: Topic :: Software Development :: Interpreters
Classifier: License :: OSI Approved :: MIT License
Classifier: Programming Language :: Python :: 3
Classifier: Operating System :: OS Independent
Requires-Python: >=3.6
License-File: LICENSE
Requires-Dist: ply
